<?xml version="1.0" encoding="utf-8" standalone="yes"?>
<Gesture Name = "rain">
	<Stroke>
		<Point X = "250" Y = "109" T = "0" Pressure = "0" />
		<Point X = "264" Y = "130" T = "0" Pressure = "0" />
		<Point X = "281" Y = "160" T = "0" Pressure = "0" />
		<Point X = "296" Y = "188" T = "0" Pressure = "0" />
		<Point X = "314" Y = "218" T = "0" Pressure = "0" />
		<Point X = "326" Y = "241" T = "0" Pressure = "0" />
		<Point X = "334" Y = "257" T = "0" Pressure = "0" />
		<Point X = "339" Y = "265" T = "0" Pressure = "0" />
	</Stroke>
	<Stroke>
		<Point X = "196" Y = "163" T = "0" Pressure = "0" />
		<Point X = "201" Y = "182" T = "0" Pressure = "0" />
		<Point X = "207" Y = "209" T = "0" Pressure = "0" />
		<Point X = "217" Y = "240" T = "0" Pressure = "0" />
		<Point X = "229" Y = "270" T = "0" Pressure = "0" />
		<Point X = "243" Y = "299" T = "0" Pressure = "0" />
		<Point X = "255" Y = "320" T = "0" Pressure = "0" />
		<Point X = "266" Y = "339" T = "0" Pressure = "0" />
		<Point X = "275" Y = "352" T = "0" Pressure = "0" />
		<Point X = "282" Y = "362" T = "0" Pressure = "0" />
		<Point X = "287" Y = "373" T = "0" Pressure = "0" />
		<Point X = "295" Y = "383" T = "0" Pressure = "0" />
		<Point X = "302" Y = "393" T = "0" Pressure = "0" />
		<Point X = "307" Y = "403" T = "0" Pressure = "0" />
	</Stroke>
</Gesture>
