<?xml version="1.0" encoding="utf-8" standalone="yes"?>
<Gesture Name = "rain">
	<Stroke>
		<Point X = "102" Y = "120" T = "0" Pressure = "0" />
		<Point X = "102" Y = "131" T = "0" Pressure = "0" />
		<Point X = "102" Y = "147" T = "0" Pressure = "0" />
		<Point X = "102" Y = "166" T = "0" Pressure = "0" />
		<Point X = "102" Y = "188" T = "0" Pressure = "0" />
		<Point X = "102" Y = "207" T = "0" Pressure = "0" />
		<Point X = "102" Y = "222" T = "0" Pressure = "0" />
		<Point X = "102" Y = "235" T = "0" Pressure = "0" />
		<Point X = "102" Y = "245" T = "0" Pressure = "0" />
		<Point X = "102" Y = "255" T = "0" Pressure = "0" />
		<Point X = "102" Y = "264" T = "0" Pressure = "0" />
		<Point X = "102" Y = "270" T = "0" Pressure = "0" />
		<Point X = "102" Y = "276" T = "0" Pressure = "0" />
		<Point X = "102" Y = "283" T = "0" Pressure = "0" />
		<Point X = "102" Y = "288" T = "0" Pressure = "0" />
		<Point X = "102" Y = "291" T = "0" Pressure = "0" />
		<Point X = "102" Y = "295" T = "0" Pressure = "0" />
		<Point X = "103" Y = "297" T = "0" Pressure = "0" />
		<Point X = "104" Y = "297" T = "0" Pressure = "0" />
		<Point X = "104" Y = "298" T = "0" Pressure = "0" />
	</Stroke>
	<Stroke>
		<Point X = "216" Y = "135" T = "0" Pressure = "0" />
		<Point X = "216" Y = "136" T = "0" Pressure = "0" />
		<Point X = "216" Y = "137" T = "0" Pressure = "0" />
		<Point X = "216" Y = "139" T = "0" Pressure = "0" />
		<Point X = "216" Y = "143" T = "0" Pressure = "0" />
		<Point X = "216" Y = "147" T = "0" Pressure = "0" />
		<Point X = "216" Y = "156" T = "0" Pressure = "0" />
		<Point X = "216" Y = "168" T = "0" Pressure = "0" />
		<Point X = "216" Y = "182" T = "0" Pressure = "0" />
		<Point X = "216" Y = "198" T = "0" Pressure = "0" />
		<Point X = "216" Y = "220" T = "0" Pressure = "0" />
		<Point X = "216" Y = "239" T = "0" Pressure = "0" />
		<Point X = "216" Y = "258" T = "0" Pressure = "0" />
		<Point X = "216" Y = "273" T = "0" Pressure = "0" />
		<Point X = "216" Y = "282" T = "0" Pressure = "0" />
		<Point X = "216" Y = "290" T = "0" Pressure = "0" />
		<Point X = "216" Y = "298" T = "0" Pressure = "0" />
		<Point X = "216" Y = "302" T = "0" Pressure = "0" />
		<Point X = "216" Y = "306" T = "0" Pressure = "0" />
		<Point X = "216" Y = "307" T = "0" Pressure = "0" />
		<Point X = "216" Y = "310" T = "0" Pressure = "0" />
	</Stroke>
</Gesture>
