<?xml version="1.0" encoding="utf-8" standalone="yes"?>
<Gesture Name = "thunder">
	<Stroke>
		<Point X = "262" Y = "101" T = "0" Pressure = "0" />
		<Point X = "261" Y = "101" T = "0" Pressure = "0" />
		<Point X = "260" Y = "102" T = "0" Pressure = "0" />
		<Point X = "259" Y = "103" T = "0" Pressure = "0" />
		<Point X = "259" Y = "104" T = "0" Pressure = "0" />
		<Point X = "258" Y = "105" T = "0" Pressure = "0" />
		<Point X = "257" Y = "106" T = "0" Pressure = "0" />
		<Point X = "255" Y = "107" T = "0" Pressure = "0" />
		<Point X = "254" Y = "108" T = "0" Pressure = "0" />
		<Point X = "253" Y = "109" T = "0" Pressure = "0" />
		<Point X = "251" Y = "110" T = "0" Pressure = "0" />
		<Point X = "249" Y = "111" T = "0" Pressure = "0" />
		<Point X = "248" Y = "113" T = "0" Pressure = "0" />
		<Point X = "247" Y = "114" T = "0" Pressure = "0" />
		<Point X = "246" Y = "115" T = "0" Pressure = "0" />
		<Point X = "244" Y = "116" T = "0" Pressure = "0" />
		<Point X = "242" Y = "118" T = "0" Pressure = "0" />
		<Point X = "240" Y = "120" T = "0" Pressure = "0" />
		<Point X = "238" Y = "121" T = "0" Pressure = "0" />
		<Point X = "236" Y = "123" T = "0" Pressure = "0" />
		<Point X = "234" Y = "125" T = "0" Pressure = "0" />
		<Point X = "229" Y = "130" T = "0" Pressure = "0" />
		<Point X = "227" Y = "132" T = "0" Pressure = "0" />
		<Point X = "226" Y = "133" T = "0" Pressure = "0" />
		<Point X = "224" Y = "135" T = "0" Pressure = "0" />
		<Point X = "219" Y = "138" T = "0" Pressure = "0" />
		<Point X = "217" Y = "141" T = "0" Pressure = "0" />
		<Point X = "214" Y = "143" T = "0" Pressure = "0" />
		<Point X = "211" Y = "144" T = "0" Pressure = "0" />
		<Point X = "209" Y = "147" T = "0" Pressure = "0" />
		<Point X = "208" Y = "148" T = "0" Pressure = "0" />
		<Point X = "206" Y = "150" T = "0" Pressure = "0" />
		<Point X = "205" Y = "152" T = "0" Pressure = "0" />
		<Point X = "203" Y = "156" T = "0" Pressure = "0" />
		<Point X = "201" Y = "157" T = "0" Pressure = "0" />
		<Point X = "199" Y = "160" T = "0" Pressure = "0" />
		<Point X = "198" Y = "162" T = "0" Pressure = "0" />
		<Point X = "196" Y = "164" T = "0" Pressure = "0" />
		<Point X = "195" Y = "167" T = "0" Pressure = "0" />
		<Point X = "193" Y = "169" T = "0" Pressure = "0" />
		<Point X = "192" Y = "171" T = "0" Pressure = "0" />
		<Point X = "191" Y = "171" T = "0" Pressure = "0" />
		<Point X = "190" Y = "173" T = "0" Pressure = "0" />
		<Point X = "190" Y = "174" T = "0" Pressure = "0" />
		<Point X = "189" Y = "176" T = "0" Pressure = "0" />
		<Point X = "189" Y = "178" T = "0" Pressure = "0" />
		<Point X = "188" Y = "178" T = "0" Pressure = "0" />
		<Point X = "188" Y = "179" T = "0" Pressure = "0" />
		<Point X = "187" Y = "180" T = "0" Pressure = "0" />
		<Point X = "187" Y = "181" T = "0" Pressure = "0" />
		<Point X = "188" Y = "181" T = "0" Pressure = "0" />
		<Point X = "189" Y = "181" T = "0" Pressure = "0" />
		<Point X = "190" Y = "181" T = "0" Pressure = "0" />
		<Point X = "192" Y = "181" T = "0" Pressure = "0" />
		<Point X = "193" Y = "181" T = "0" Pressure = "0" />
		<Point X = "196" Y = "181" T = "0" Pressure = "0" />
		<Point X = "199" Y = "181" T = "0" Pressure = "0" />
		<Point X = "201" Y = "181" T = "0" Pressure = "0" />
		<Point X = "204" Y = "181" T = "0" Pressure = "0" />
		<Point X = "207" Y = "181" T = "0" Pressure = "0" />
		<Point X = "211" Y = "181" T = "0" Pressure = "0" />
		<Point X = "214" Y = "181" T = "0" Pressure = "0" />
		<Point X = "217" Y = "181" T = "0" Pressure = "0" />
		<Point X = "221" Y = "181" T = "0" Pressure = "0" />
		<Point X = "224" Y = "181" T = "0" Pressure = "0" />
		<Point X = "228" Y = "181" T = "0" Pressure = "0" />
		<Point X = "230" Y = "181" T = "0" Pressure = "0" />
		<Point X = "234" Y = "181" T = "0" Pressure = "0" />
		<Point X = "238" Y = "181" T = "0" Pressure = "0" />
		<Point X = "241" Y = "181" T = "0" Pressure = "0" />
		<Point X = "245" Y = "181" T = "0" Pressure = "0" />
		<Point X = "247" Y = "181" T = "0" Pressure = "0" />
		<Point X = "251" Y = "181" T = "0" Pressure = "0" />
		<Point X = "252" Y = "181" T = "0" Pressure = "0" />
		<Point X = "254" Y = "181" T = "0" Pressure = "0" />
		<Point X = "256" Y = "181" T = "0" Pressure = "0" />
		<Point X = "257" Y = "181" T = "0" Pressure = "0" />
		<Point X = "259" Y = "181" T = "0" Pressure = "0" />
		<Point X = "261" Y = "181" T = "0" Pressure = "0" />
		<Point X = "263" Y = "181" T = "0" Pressure = "0" />
		<Point X = "264" Y = "181" T = "0" Pressure = "0" />
		<Point X = "264" Y = "182" T = "0" Pressure = "0" />
		<Point X = "264" Y = "183" T = "0" Pressure = "0" />
		<Point X = "264" Y = "185" T = "0" Pressure = "0" />
		<Point X = "264" Y = "186" T = "0" Pressure = "0" />
		<Point X = "263" Y = "186" T = "0" Pressure = "0" />
		<Point X = "261" Y = "189" T = "0" Pressure = "0" />
		<Point X = "258" Y = "191" T = "0" Pressure = "0" />
		<Point X = "257" Y = "192" T = "0" Pressure = "0" />
		<Point X = "255" Y = "196" T = "0" Pressure = "0" />
		<Point X = "252" Y = "198" T = "0" Pressure = "0" />
		<Point X = "251" Y = "201" T = "0" Pressure = "0" />
		<Point X = "248" Y = "204" T = "0" Pressure = "0" />
		<Point X = "246" Y = "207" T = "0" Pressure = "0" />
		<Point X = "244" Y = "210" T = "0" Pressure = "0" />
		<Point X = "240" Y = "215" T = "0" Pressure = "0" />
		<Point X = "237" Y = "219" T = "0" Pressure = "0" />
		<Point X = "230" Y = "226" T = "0" Pressure = "0" />
		<Point X = "228" Y = "230" T = "0" Pressure = "0" />
		<Point X = "223" Y = "233" T = "0" Pressure = "0" />
		<Point X = "220" Y = "237" T = "0" Pressure = "0" />
		<Point X = "216" Y = "239" T = "0" Pressure = "0" />
		<Point X = "214" Y = "241" T = "0" Pressure = "0" />
		<Point X = "211" Y = "245" T = "0" Pressure = "0" />
		<Point X = "208" Y = "247" T = "0" Pressure = "0" />
		<Point X = "206" Y = "250" T = "0" Pressure = "0" />
		<Point X = "204" Y = "251" T = "0" Pressure = "0" />
		<Point X = "202" Y = "254" T = "0" Pressure = "0" />
		<Point X = "200" Y = "255" T = "0" Pressure = "0" />
		<Point X = "199" Y = "256" T = "0" Pressure = "0" />
		<Point X = "197" Y = "258" T = "0" Pressure = "0" />
		<Point X = "194" Y = "259" T = "0" Pressure = "0" />
		<Point X = "193" Y = "261" T = "0" Pressure = "0" />
		<Point X = "191" Y = "262" T = "0" Pressure = "0" />
		<Point X = "190" Y = "263" T = "0" Pressure = "0" />
		<Point X = "188" Y = "265" T = "0" Pressure = "0" />
		<Point X = "187" Y = "266" T = "0" Pressure = "0" />
		<Point X = "186" Y = "267" T = "0" Pressure = "0" />
	</Stroke>
</Gesture>
